{
  "schemaVersion": "1.0.0",
  "shape": "snowflake",
  "points": [
    {
      "x": 114,
      "y": 10
    },
    {
      "x": 125,
      "y": 59
    },
    {
      "x": 126,
      "y": 85
    },
    {
      "x": 119,
      "y": 130
    },
    {
      "x": 0,
      "y": 53
    },
    {
      "x": 25,
      "y": 59
    },
    {
      "x": 79,
      "y": 61
    },
    {
      "x": 193,
      "y": 72
    },
    {
      "x": 255,
      "y": 84
    },
    {
      "x": 212,
      "y": 22
    },
    {
      "x": 151,
      "y": 42
    },
    {
      "x": 120,
      "y": 58
    },
    {
      "x": 84,
      "y": 99
    },
    {
      "x": 54,
      "y": 125
    },
    {
      "x": 76,
      "y": 0
    },
    {
      "x": 75,
      "y": 13
    },
    {
      "x": 111,
      "y": 48
    },
    {
      "x": 130,
      "y": 61
    },
    {
      "x": 143,
      "y": 76
    },
    {
      "x": 153,
      "y": 99
    },
    {
      "x": 180,
      "y": 132
    },
    {
      "x": 180,
      "y": 126
    }
  ],
  "capturedAt": "2026-05-07T01:10:41.759Z",
  "captureContext": {
    "device": "quickdraw",
    "os": "unknown",
    "viewport": {
      "w": 0,
      "h": 0
    },
    "pixelRatio": 1,
    "inputType": "mouse"
  },
  "importedFrom": "quickdraw:snowflake#6106024316502016"
}