{
  "savedAt": "2026-05-07T01:10:24.773Z",
  "shape": "wave",
  "points": [
    {
      "x": 1,
      "y": 8
    },
    {
      "x": 7,
      "y": 12
    },
    {
      "x": 22,
      "y": 12
    },
    {
      "x": 41,
      "y": 1
    },
    {
      "x": 49,
      "y": 14
    },
    {
      "x": 58,
      "y": 17
    },
    {
      "x": 63,
      "y": 16
    },
    {
      "x": 74,
      "y": 4
    },
    {
      "x": 91,
      "y": 15
    },
    {
      "x": 98,
      "y": 14
    },
    {
      "x": 105,
      "y": 7
    },
    {
      "x": 116,
      "y": 18
    },
    {
      "x": 129,
      "y": 20
    },
    {
      "x": 139,
      "y": 14
    },
    {
      "x": 146,
      "y": 5
    },
    {
      "x": 152,
      "y": 15
    },
    {
      "x": 163,
      "y": 18
    },
    {
      "x": 171,
      "y": 14
    },
    {
      "x": 180,
      "y": 0
    },
    {
      "x": 196,
      "y": 10
    },
    {
      "x": 203,
      "y": 9
    },
    {
      "x": 210,
      "y": 1
    },
    {
      "x": 224,
      "y": 8
    },
    {
      "x": 236,
      "y": 3
    },
    {
      "x": 247,
      "y": 6
    },
    {
      "x": 255,
      "y": 2
    }
  ],
  "importedFrom": "quickdraw:ocean#4796415777701888"
}