{
  "schemaVersion": "1.0.0",
  "shape": "wave",
  "points": [
    {
      "x": 22,
      "y": 32
    },
    {
      "x": 43,
      "y": 9
    },
    {
      "x": 59,
      "y": 0
    },
    {
      "x": 62,
      "y": 1
    },
    {
      "x": 64,
      "y": 7
    },
    {
      "x": 65,
      "y": 46
    },
    {
      "x": 74,
      "y": 49
    },
    {
      "x": 98,
      "y": 27
    },
    {
      "x": 104,
      "y": 26
    },
    {
      "x": 104,
      "y": 54
    },
    {
      "x": 109,
      "y": 63
    },
    {
      "x": 121,
      "y": 58
    },
    {
      "x": 143,
      "y": 29
    },
    {
      "x": 152,
      "y": 23
    },
    {
      "x": 159,
      "y": 47
    },
    {
      "x": 167,
      "y": 52
    },
    {
      "x": 192,
      "y": 27
    },
    {
      "x": 202,
      "y": 23
    },
    {
      "x": 206,
      "y": 27
    },
    {
      "x": 208,
      "y": 55
    },
    {
      "x": 214,
      "y": 57
    },
    {
      "x": 248,
      "y": 25
    },
    {
      "x": 253,
      "y": 23
    },
    {
      "x": 255,
      "y": 52
    },
    {
      "x": 33,
      "y": 34
    },
    {
      "x": 25,
      "y": 41
    },
    {
      "x": 0,
      "y": 49
    },
    {
      "x": 86,
      "y": 75
    },
    {
      "x": 116,
      "y": 87
    },
    {
      "x": 151,
      "y": 84
    },
    {
      "x": 153,
      "y": 80
    },
    {
      "x": 123,
      "y": 68
    },
    {
      "x": 107,
      "y": 66
    },
    {
      "x": 103,
      "y": 68
    },
    {
      "x": 100,
      "y": 76
    },
    {
      "x": 101,
      "y": 86
    },
    {
      "x": 105,
      "y": 96
    }
  ],
  "capturedAt": "2026-05-07T01:10:24.771Z",
  "captureContext": {
    "device": "quickdraw",
    "os": "unknown",
    "viewport": {
      "w": 0,
      "h": 0
    },
    "pixelRatio": 1,
    "inputType": "mouse"
  },
  "importedFrom": "quickdraw:ocean#5647395226386432"
}